configshell/__init__.py
configshell/console.py
configshell/log.py
configshell/node.py
configshell/prefs.py
configshell/shell.py
configshell_fb.py
configshell_fb-2.0.2.dist-info/METADATA
configshell_fb-2.0.2.dist-info/WHEEL
configshell_fb-2.0.2.dist-info/licenses/COPYING
configshell_fb-2.0.2.dist-info/RECORD
