Metadata-Version: 2.4
Name: configshell-fb
Version: 2.0.2
Summary: A framework to implement simple but nice CLIs.
Project-URL: Homepage, http://github.com/open-iscsi/configshell-fb
Author-email: Andy Grover <agrover@redhat.com>, Jerome Martin <jxm@risingtidesystems.com>
Maintainer-email: Maurizio Lombardi <mlombard@redhat.com>
License-Expression: Apache-2.0
License-File: COPYING
Classifier: License :: OSI Approved :: Apache Software License
Classifier: Programming Language :: Python :: 3
Classifier: Programming Language :: Python :: 3.9
Classifier: Programming Language :: Python :: 3.12
Requires-Python: >=3.9
Requires-Dist: pyparsing<4,>=2.4.7
